Metadata-Version: 2.1
Name: odoo13-addon-stock-reception-screen-qty-by-packaging
Version: 13.0.1.0.1.dev5
Summary: Glue module for `stock_product_qty_by_packaging` and `stock_vertical_lift`.
Home-page: https://github.com/OCA/wms
Author: Camptocamp, Odoo Community Association (OCA)
Author-email: support@odoo-community.org
License: LGPL-3
Platform: UNKNOWN
Classifier: Programming Language :: Python
Classifier: Framework :: Odoo
Classifier: Framework :: Odoo :: 13.0
Classifier: License :: OSI Approved :: GNU Lesser General Public License v3 (LGPLv3)
Classifier: Development Status :: 3 - Alpha
Requires-Python: >=3.5
Requires-Dist: odoo13-addon-stock-product-qty-by-packaging
Requires-Dist: odoo13-addon-stock-reception-screen
Requires-Dist: odoo <13.1dev,>=13.0a
